{
	"type": "minecraft:chest",
	"pools": [
		{
			"rolls": 5,
			"entries": [
				{
					"type": "minecraft:item",
					"weight": 50,
					"name": "minecraft:moss_block",
					"functions": [
						{
							"function": "minecraft:set_count",
							"count": {
								"min": 1,
								"max": 10
							}
						}
					]
				},
				{
					"type": "minecraft:item",
					"weight": 20,
					"name": "minecraft:moss_carpet",
					"functions": [
						{
							"function": "minecraft:set_count",
							"count": {
								"min": 1,
								"max": 5
							}
						}
					]
				},
				{
					"type": "minecraft:item",
					"weight": 1,
					"name": "minecraft:vine",
					"functions": [
						{
							"function": "minecraft:set_count",
							"count": {
								"min": 1,
								"max": 5
							}
						}
					]
				},
				{
					"type": "minecraft:item",
					"weight": 10,
					"name": "minecraft:grass"
				},
				{
					"type": "minecraft:item",
					"weight": 5,
					"name": "minecraft:fern",
					"functions": [
						{
							"function": "minecraft:set_count",
							"count": {
								"min": 1,
								"max": 5
							}
						}
					]
				},
				{
					"type": "minecraft:item",
					"weight": 5,
					"name": "minecraft:hanging_roots",
					"functions": [
						{
							"function": "minecraft:set_count",
							"count": {
								"min": 1,
								"max": 5
							}
						}
					]
				},
				{
					"type": "minecraft:item",
					"weight": 5,
					"name": "minecraft:red_mushroom",
					"functions": [
						{
							"function": "minecraft:set_count",
							"count": {
								"min": 1,
								"max": 5
							}
						}
					]
				},
				{
					"type": "minecraft:item",
					"weight": 5,
					"name": "minecraft:brown_mushroom",
					"functions": [
						{
							"function": "minecraft:set_count",
							"count": {
								"min": 1,
								"max": 5
							}
						}
					]
				}
			]
		},
    {
      "rolls": 1,
      "entries": [
        {
          "type": "minecraft:loot_table",
          "name": "exosphere:chests/enderio_loot"
        }
      ]
    },
    {
      "rolls": 1,
      "entries": [
        {
          "type": "minecraft:loot_table",
          "name": "exosphere:chests/refinedstorage_loot"
        }
      ]
    },
    {
      "rolls": 1,
      "entries": [
        {
          "type": "minecraft:loot_table",
          "name": "exosphere:chests/simplefarming_loot"
        }
      ]
    },
    {
      "rolls": 2,
      "entries": [
        {
          "type": "minecraft:loot_table",
          "name": "exosphere:chests/immersive_armors_loot"
        }
      ]
    },
    {
      "rolls": 1,
      "entries": [
        {
          "type": "minecraft:loot_table",
          "name": "exosphere:chests/ancient_notes"
        }
      ]
    }
	]
}
